rawpyreindexerb.so
rawpyreindexerc.so
pyreindexer/CMakeLists.txt
pyreindexer/__init__.py
pyreindexer/exceptions.py
pyreindexer/index_definition.py
pyreindexer/index_search_params.py
pyreindexer/point.py
pyreindexer/query.py
pyreindexer/query_results.py
pyreindexer/raiser_mixin.py
pyreindexer/rx_connector.py
pyreindexer/transaction.py
pyreindexer/example/main.py
pyreindexer/lib/include/pyobjtools.cc
pyreindexer/lib/include/pyobjtools.h
pyreindexer/lib/include/query_wrapper.cc
pyreindexer/lib/include/query_wrapper.h
pyreindexer/lib/include/queryresults_wrapper.h
pyreindexer/lib/include/transaction_wrapper.h
pyreindexer/lib/src/rawpyreindexer.cc
pyreindexer/lib/src/rawpyreindexer.h
pyreindexer/lib/src/reindexerinterface.cc
pyreindexer/lib/src/reindexerinterface.h
pyreindexer/tests/__init__.py
pyreindexer/tests/conftest.py
pyreindexer/tests/embedding_tests/__init__.py
pyreindexer/tests/embedding_tests/test_query.py
pyreindexer/tests/helpers/__init__.py
pyreindexer/tests/helpers/api.py
pyreindexer/tests/helpers/base_helper.py
pyreindexer/tests/helpers/check_helper.py
pyreindexer/tests/helpers/log_helper.py
pyreindexer/tests/helpers/matchers.py
pyreindexer/tests/helpers/server_helper.py
pyreindexer/tests/helpers/transaction.py
pyreindexer/tests/test_data/__init__.py
pyreindexer/tests/test_data/auth.py
pyreindexer/tests/test_data/constants.py
pyreindexer/tests/tests/__init__.py
pyreindexer/tests/tests/test_auth.py
pyreindexer/tests/tests/test_builtin.py
pyreindexer/tests/tests/test_cproto.py
pyreindexer/tests/tests/test_database.py
pyreindexer/tests/tests/test_index.py
pyreindexer/tests/tests/test_items.py
pyreindexer/tests/tests/test_metadata.py
pyreindexer/tests/tests/test_namespace.py
pyreindexer/tests/tests/test_query.py
pyreindexer/tests/tests/test_sql.py
pyreindexer/tests/tests/test_transaction.py
pyreindexer.libs/libgomp-870cb1d0.so.1.0.0
pyreindexer.libs/libleveldb-cb4f10aa.so.1.22.0
pyreindexer-0.5.100000.dist-info/LICENSE
pyreindexer-0.5.100000.dist-info/METADATA
pyreindexer-0.5.100000.dist-info/WHEEL
pyreindexer-0.5.100000.dist-info/top_level.txt
pyreindexer-0.5.100000.dist-info/RECORD
