Metadata-Version: 2.4
Name: pyreindexer
Version: 0.5.100000
Summary: A connector that allows to interact with Reindexer. Reindexer static library or reindexer-dev package must be installed
Home-page: https://github.com/Restream/reindexer
Download-URL: https://github.com/Restream/reindexer-py
Author: Igor Tulmentyev
Author-email: contactus@reindexer.io
Maintainer: Reindexer Team
Maintainer-email: contactus@reindexer.io
License: Apache License 2.0
Project-URL: Documentation, https://reindexer.io/
Project-URL: Telegram chat, https://t.me/reindexer
Keywords: reindexer,reindexer-py,in-memory-database,database,python,connector
Platform: Ubuntu
Platform: Debian
Platform: ALT Linux
Platform: RED OS
Platform: Astra Linux
Platform: MacOS
Classifier: Development Status :: 4 - Beta
Classifier: Environment :: Console
Classifier: Intended Audience :: End Users/Desktop
Classifier: Intended Audience :: Developers
Classifier: Natural Language :: Russian
Classifier: Operating System :: MacOS
Classifier: Operating System :: POSIX :: Linux
Classifier: Programming Language :: Python
Classifier: Programming Language :: Python :: 3 :: Only
Classifier: Programming Language :: Python :: 3.8
Classifier: Programming Language :: Python :: 3.9
Classifier: Programming Language :: Python :: 3.10
Classifier: Programming Language :: Python :: 3.11
Classifier: Programming Language :: Python :: 3.12
Classifier: Programming Language :: Python :: 3.13
Classifier: Programming Language :: Python :: Implementation
Classifier: Programming Language :: Python :: Implementation :: CPython
Classifier: Programming Language :: Python :: Implementation :: PyPy
Classifier: Topic :: Database
Classifier: Topic :: Database :: Database Engines/Servers
Classifier: Topic :: Software Development
Classifier: Topic :: Software Development :: Libraries
Classifier: Topic :: Software Development :: Libraries :: Python Modules
Classifier: Topic :: Software Development :: Libraries :: Application Frameworks
Requires-Python: >=3.8
License-File: LICENSE
Requires-Dist: PyHamcrest==2.0.2
Requires-Dist: pytest>=6.2.5
Requires-Dist: requests>=2.26.0
Dynamic: author
Dynamic: author-email
Dynamic: classifier
Dynamic: description
Dynamic: description-content-type
Dynamic: download-url
Dynamic: home-page
Dynamic: keywords
Dynamic: license
Dynamic: license-file
Dynamic: maintainer
Dynamic: maintainer-email
Dynamic: platform
Dynamic: project-url
Dynamic: requires-dist
Dynamic: requires-python
Dynamic: summary
